{
    "playerStats": [
        {
            "stats": {
                "mins_played": [
                    23,
                    1
                ],
                "goals": [
                    0,
                    0
                ],
                "goal_assist": [
                    0,
                    0
                ],
                "offtarget_att_assist": [
                    0,
                    0
                ],
                "pen_area_entries": [
                    0,
                    0
                ],
                "penalty_won": [
                    0,
                    0
                ],
                "penalty_save": [
                    0,
                    0
                ],
                "saves": [
                    0,
                    0
                ],
                "effective_clearance": [
                    0,
                    0
                ],
                "penalty_failed": [
                    0,
                    0
                ],
                "own_goals": [
                    0,
                    0
                ],
                "goals_conceded": [
                    0,
                    0
                ],
                "yellow_card": [
                    0,
                    0
                ],
                "second_yellow_card": [
                    0,
                    0
                ],
                "red_card": [
                    0,
                    0
                ],
                "total_scoring_att": [
                    0,
                    0
                ],
                "won_contest": [
                    0,
                    0
                ],
                "ball_recovery": [
                    3,
                    0
                ],
                "poss_lost_all": [
                    2,
                    0
                ],
                "penalty_conceded": [
                    0,
                    0
                ],
                "marca_points": [
                    -1,
                    1
                ]
            },
            "weekNumber": 2,
            "totalPoints": 2,
            "isInIdealFormation": false
        },
        {
            "stats": {
                "mins_played": [
                    0,
                    0
                ],
                "goals": [
                    0,
                    0
                ],
                "goal_assist": [
                    0,
                    0
                ],
                "offtarget_att_assist": [
                    0,
                    0
                ],
                "pen_area_entries": [
                    0,
                    0
                ],
                "penalty_won": [
                    0,
                    0
                ],
                "penalty_save": [
                    0,
                    0
                ],
                "saves": [
                    0,
                    0
                ],
                "effective_clearance": [
                    0,
                    0
                ],
                "penalty_failed": [
                    0,
                    0
                ],
                "own_goals": [
                    0,
                    0
                ],
                "goals_conceded": [
                    0,
                    0
                ],
                "yellow_card": [
                    0,
                    0
                ],
                "second_yellow_card": [
                    0,
                    0
                ],
                "red_card": [
                    0,
                    0
                ],
                "total_scoring_att": [
                    0,
                    0
                ],
                "won_contest": [
                    0,
                    0
                ],
                "ball_recovery": [
                    0,
                    0
                ],
                "poss_lost_all": [
                    0,
                    0
                ],
                "penalty_conceded": [
                    0,
                    0
                ],
                "marca_points": [
                    -1,
                    0
                ]
            },
            "weekNumber": 6,
            "totalPoints": 0,
            "isInIdealFormation": false
        },
        {
            "stats": {
                "mins_played": [
                    45,
                    1
                ],
                "goals": [
                    0,
                    0
                ],
                "goal_assist": [
                    0,
                    0
                ],
                "offtarget_att_assist": [
                    0,
                    0
                ],
                "pen_area_entries": [
                    0,
                    0
                ],
                "penalty_won": [
                    0,
                    0
                ],
                "penalty_save": [
                    0,
                    0
                ],
                "saves": [
                    0,
                    0
                ],
                "effective_clearance": [
                    1,
                    0
                ],
                "penalty_failed": [
                    0,
                    0
                ],
                "own_goals": [
                    0,
                    0
                ],
                "goals_conceded": [
                    1,
                    0
                ],
                "yellow_card": [
                    0,
                    0
                ],
                "second_yellow_card": [
                    0,
                    0
                ],
                "red_card": [
                    0,
                    0
                ],
                "total_scoring_att": [
                    0,
                    0
                ],
                "won_contest": [
                    0,
                    0
                ],
                "ball_recovery": [
                    3,
                    0
                ],
                "poss_lost_all": [
                    6,
                    0
                ],
                "penalty_conceded": [
                    0,
                    0
                ],
                "marca_points": [
                    -1,
                    0
                ]
            },
            "weekNumber": 7,
            "totalPoints": 1,
            "isInIdealFormation": false
        },
        {
            "stats": {
                "mins_played": [
                    0,
                    0
                ],
                "goals": [
                    0,
                    0
                ],
                "goal_assist": [
                    0,
                    0
                ],
                "offtarget_att_assist": [
                    0,
                    0
                ],
                "pen_area_entries": [
                    0,
                    0
                ],
                "penalty_won": [
                    0,
                    0
                ],
                "penalty_save": [
                    0,
                    0
                ],
                "saves": [
                    0,
                    0
                ],
                "effective_clearance": [
                    0,
                    0
                ],
                "penalty_failed": [
                    0,
                    0
                ],
                "own_goals": [
                    0,
                    0
                ],
                "goals_conceded": [
                    0,
                    0
                ],
                "yellow_card": [
                    0,
                    0
                ],
                "second_yellow_card": [
                    0,
                    0
                ],
                "red_card": [
                    0,
                    0
                ],
                "total_scoring_att": [
                    0,
                    0
                ],
                "won_contest": [
                    0,
                    0
                ],
                "ball_recovery": [
                    0,
                    0
                ],
                "poss_lost_all": [
                    0,
                    0
                ],
                "penalty_conceded": [
                    0,
                    0
                ],
                "marca_points": [
                    -1,
                    0
                ]
            },
            "weekNumber": 8,
            "totalPoints": 0,
            "isInIdealFormation": false
        },
        {
            "stats": {
                "mins_played": [
                    0,
                    0
                ],
                "goals": [
                    0,
                    0
                ],
                "goal_assist": [
                    0,
                    0
                ],
                "offtarget_att_assist": [
                    0,
                    0
                ],
                "pen_area_entries": [
                    0,
                    0
                ],
                "penalty_won": [
                    0,
                    0
                ],
                "penalty_save": [
                    0,
                    0
                ],
                "saves": [
                    0,
                    0
                ],
                "effective_clearance": [
                    0,
                    0
                ],
                "penalty_failed": [
                    0,
                    0
                ],
                "own_goals": [
                    0,
                    0
                ],
                "goals_conceded": [
                    0,
                    0
                ],
                "yellow_card": [
                    0,
                    0
                ],
                "second_yellow_card": [
                    0,
                    0
                ],
                "red_card": [
                    0,
                    0
                ],
                "total_scoring_att": [
                    0,
                    0
                ],
                "won_contest": [
                    0,
                    0
                ],
                "ball_recovery": [
                    0,
                    0
                ],
                "poss_lost_all": [
                    0,
                    0
                ],
                "penalty_conceded": [
                    0,
                    0
                ],
                "marca_points": [
                    -1,
                    0
                ]
            },
            "weekNumber": 9,
            "totalPoints": 0,
            "isInIdealFormation": false
        },
        {
            "stats": {
                "mins_played": [
                    0,
                    0
                ],
                "goals": [
                    0,
                    0
                ],
                "goal_assist": [
                    0,
                    0
                ],
                "offtarget_att_assist": [
                    0,
                    0
                ],
                "pen_area_entries": [
                    0,
                    0
                ],
                "penalty_won": [
                    0,
                    0
                ],
                "penalty_save": [
                    0,
                    0
                ],
                "saves": [
                    0,
                    0
                ],
                "effective_clearance": [
                    0,
                    0
                ],
                "penalty_failed": [
                    0,
                    0
                ],
                "own_goals": [
                    0,
                    0
                ],
                "goals_conceded": [
                    0,
                    0
                ],
                "yellow_card": [
                    0,
                    0
                ],
                "second_yellow_card": [
                    0,
                    0
                ],
                "red_card": [
                    0,
                    0
                ],
                "total_scoring_att": [
                    0,
                    0
                ],
                "won_contest": [
                    0,
                    0
                ],
                "ball_recovery": [
                    0,
                    0
                ],
                "poss_lost_all": [
                    0,
                    0
                ],
                "penalty_conceded": [
                    0,
                    0
                ],
                "marca_points": [
                    -1,
                    0
                ]
            },
            "weekNumber": 10,
            "totalPoints": 0,
            "isInIdealFormation": false
        },
        {
            "stats": {
                "mins_played": [
                    0,
                    0
                ],
                "goals": [
                    0,
                    0
                ],
                "goal_assist": [
                    0,
                    0
                ],
                "offtarget_att_assist": [
                    0,
                    0
                ],
                "pen_area_entries": [
                    0,
                    0
                ],
                "penalty_won": [
                    0,
                    0
                ],
                "penalty_save": [
                    0,
                    0
                ],
                "saves": [
                    0,
                    0
                ],
                "effective_clearance": [
                    0,
                    0
                ],
                "penalty_failed": [
                    0,
                    0
                ],
                "own_goals": [
                    0,
                    0
                ],
                "goals_conceded": [
                    0,
                    0
                ],
                "yellow_card": [
                    0,
                    0
                ],
                "second_yellow_card": [
                    0,
                    0
                ],
                "red_card": [
                    0,
                    0
                ],
                "total_scoring_att": [
                    0,
                    0
                ],
                "won_contest": [
                    0,
                    0
                ],
                "ball_recovery": [
                    0,
                    0
                ],
                "poss_lost_all": [
                    0,
                    0
                ],
                "penalty_conceded": [
                    0,
                    0
                ],
                "marca_points": [
                    -1,
                    0
                ]
            },
            "weekNumber": 11,
            "totalPoints": 0,
            "isInIdealFormation": false
        },
        {
            "stats": {
                "mins_played": [
                    0,
                    0
                ],
                "goals": [
                    0,
                    0
                ],
                "goal_assist": [
                    0,
                    0
                ],
                "offtarget_att_assist": [
                    0,
                    0
                ],
                "pen_area_entries": [
                    0,
                    0
                ],
                "penalty_won": [
                    0,
                    0
                ],
                "penalty_save": [
                    0,
                    0
                ],
                "saves": [
                    0,
                    0
                ],
                "effective_clearance": [
                    0,
                    0
                ],
                "penalty_failed": [
                    0,
                    0
                ],
                "own_goals": [
                    0,
                    0
                ],
                "goals_conceded": [
                    0,
                    0
                ],
                "yellow_card": [
                    0,
                    0
                ],
                "second_yellow_card": [
                    0,
                    0
                ],
                "red_card": [
                    0,
                    0
                ],
                "total_scoring_att": [
                    0,
                    0
                ],
                "won_contest": [
                    0,
                    0
                ],
                "ball_recovery": [
                    0,
                    0
                ],
                "poss_lost_all": [
                    0,
                    0
                ],
                "penalty_conceded": [
                    0,
                    0
                ],
                "marca_points": [
                    -1,
                    0
                ]
            },
            "weekNumber": 12,
            "totalPoints": 0,
            "isInIdealFormation": false
        },
        {
            "stats": {
                "mins_played": [
                    0,
                    0
                ],
                "goals": [
                    0,
                    0
                ],
                "goal_assist": [
                    0,
                    0
                ],
                "offtarget_att_assist": [
                    0,
                    0
                ],
                "pen_area_entries": [
                    0,
                    0
                ],
                "penalty_won": [
                    0,
                    0
                ],
                "penalty_save": [
                    0,
                    0
                ],
                "saves": [
                    0,
                    0
                ],
                "effective_clearance": [
                    0,
                    0
                ],
                "penalty_failed": [
                    0,
                    0
                ],
                "own_goals": [
                    0,
                    0
                ],
                "goals_conceded": [
                    0,
                    0
                ],
                "yellow_card": [
                    0,
                    0
                ],
                "second_yellow_card": [
                    0,
                    0
                ],
                "red_card": [
                    0,
                    0
                ],
                "total_scoring_att": [
                    0,
                    0
                ],
                "won_contest": [
                    0,
                    0
                ],
                "ball_recovery": [
                    0,
                    0
                ],
                "poss_lost_all": [
                    0,
                    0
                ],
                "penalty_conceded": [
                    0,
                    0
                ],
                "marca_points": [
                    -1,
                    0
                ]
            },
            "weekNumber": 13,
            "totalPoints": 0,
            "isInIdealFormation": false
        }
    ],
    "points": 3,
    "weekPoints": 0,
    "averagePoints": 0.3333333333333333,
    "id": "1695",
    "team": {
        "badgeColor": "https://assets-fantasy.llt-services.com/teambadge/t407/color/t407_ud-las-palmas.png",
        "badgeGray": "https://assets-fantasy.llt-services.com/teambadge/t407/gray/t407_ud-las-palmas.png",
        "badgeWhite": "https://assets-fantasy.llt-services.com/teambadge/t407/white/t407_ud-las-palmas.png",
        "name": "UD Las Palmas",
        "id": "31",
        "shortName": "LPA",
        "slug": "ud-las-palmas",
        "dspId": 181,
        "store": ""
    },
    "name": "Daley Sinkgraven",
    "nickname": "Sinkgraven",
    "slug": "daley-sinkgraven",
    "positionId": 2,
    "position": "Defensa",
    "marketValue": {
        "17/08/2023": 4195827,
        "18/08/2023": 4046098,
        "19/08/2023": 3931309,
        "20/08/2023": 3806826,
        "21/08/2023": 3686017,
        "22/08/2023": 3565993,
        "23/08/2023": 3445367,
        "24/08/2023": 3332608,
        "25/08/2023": 3228795,
        "26/08/2023": 3125846,
        "27/08/2023": 3022794,
        "28/08/2023": 2923009,
        "29/08/2023": 2825920,
        "30/08/2023": 2728870,
        "31/08/2023": 2636853,
        "01/09/2023": 2549014,
        "02/09/2023": 2465498,
        "03/09/2023": 2384316,
        "04/09/2023": 2305419,
        "05/09/2023": 2224873,
        "06/09/2023": 2149748,
        "07/09/2023": 2077941,
        "08/09/2023": 2010130,
        "09/09/2023": 1946168,
        "10/09/2023": 1884668,
        "11/09/2023": 1824401,
        "12/09/2023": 1766789,
        "13/09/2023": 1712277,
        "14/09/2023": 1659809,
        "15/09/2023": 1609049,
        "16/09/2023": 1560325,
        "17/09/2023": 1514848,
        "18/09/2023": 1469885,
        "19/09/2023": 1425545,
        "20/09/2023": 1381985,
        "21/09/2023": 1339278,
        "22/09/2023": 1298505,
        "23/09/2023": 1259552,
        "24/09/2023": 1224245,
        "25/09/2023": 1189954,
        "26/09/2023": 1154673,
        "27/09/2023": 1119904,
        "28/09/2023": 1088210,
        "29/09/2023": 1057703,
        "30/09/2023": 1027617,
        "01/10/2023": 999779,
        "02/10/2023": 973043,
        "03/10/2023": 946832,
        "04/10/2023": 921308,
        "05/10/2023": 896554,
        "06/10/2023": 873788,
        "07/10/2023": 852368,
        "08/10/2023": 834039,
        "09/10/2023": 816198,
        "10/10/2023": 797795,
        "11/10/2023": 779465,
        "12/10/2023": 762927,
        "13/10/2023": 747916,
        "14/10/2023": 734279,
        "15/10/2023": 722687,
        "16/10/2023": 712670,
        "17/10/2023": 703165,
        "18/10/2023": 694615,
        "19/10/2023": 687100,
        "20/10/2023": 680599,
        "21/10/2023": 674769,
        "22/10/2023": 670921,
        "23/10/2023": 666017,
        "24/10/2023": 659315,
        "25/10/2023": 650955,
        "26/10/2023": 641474,
        "27/10/2023": 633415,
        "28/10/2023": 626081,
        "29/10/2023": 621238,
        "30/10/2023": 616055,
        "31/10/2023": 609489,
        "01/11/2023": 602274,
        "02/11/2023": 595676,
        "03/11/2023": 589367,
        "04/11/2023": 583742,
        "05/11/2023": 581182,
        "06/11/2023": 578090,
        "07/11/2023": 574049,
        "08/11/2023": 569032,
        "09/11/2023": 563606,
        "10/11/2023": 558884,
        "11/11/2023": 554378,
        "12/11/2023": 552441,
        "13/11/2023": 549625
    },
    "playerStatus": "ok"
}